{
  "license_info": "CC BY 4.0 (creativecommons.org/licenses/by/4.0) from Bundesnetzagentur | SMARD.de",
  "_license_info_comment": "Data licensing and attribution. Data sourced from SMARD.de (Strombörse Market Data, German electricity exchange operated by Bundesnetzagentur). Licensed under Creative Commons Attribution 4.0.",

  "unix_seconds": [
    1767135600,
    "_comment": "2025-12-31 10:00:00 UTC - First timestamp for requested date range",
    1767136500,
    "_comment": "2025-12-31 10:15:00 UTC - Second timestamp (15-minute interval)",
    1767137400,
    "_comment": "2025-12-31 10:30:00 UTC - Third timestamp",
    1767138300,
    "_comment": "2025-12-31 10:45:00 UTC",
    1767139200,
    "_comment": "2025-12-31 11:00:00 UTC",
    1767140100,
    "_comment": "2025-12-31 11:15:00 UTC",
    1767141000,
    "_comment": "...continues with 15-minute intervals through the requested date range"
  ],
  "_unix_seconds_comment": "Array of Unix timestamps (seconds since January 1, 1970, 00:00:00 UTC). Each timestamp represents the start of a 15-minute trading interval. Timestamps increment by 900 seconds (15 minutes × 60 seconds). Timezone is always UTC.",

  "price": [
    94.87,
    "_comment": "Price at 2025-12-31 10:00:00 UTC = 94.87 EUR/MWh",
    90.31,
    "_comment": "Price at 2025-12-31 10:15:00 UTC = 90.31 EUR/MWh",
    86.19,
    "_comment": "Price at 2025-12-31 10:30:00 UTC = 86.19 EUR/MWh (declining trend)",
    81.04,
    "_comment": "Price at 2025-12-31 10:45:00 UTC = 81.04 EUR/MWh",
    90.11,
    "_comment": "Price at 2025-12-31 11:00:00 UTC = 90.11 EUR/MWh (price increased)",
    83.48,
    "_comment": "Price at 2025-12-31 11:15:00 UTC = 83.48 EUR/MWh",
    82.69,
    "_comment": "...continues with prices corresponding to each 15-minute interval"
  ],
  "_price_comment": "Array of floating-point numbers representing electricity prices in EUR/MWh. Each price at index i corresponds to the timestamp at unix_seconds[i]. Prices can range from negative (oversupply, rare) to 200+ EUR/MWh depending on market conditions. Decimals represent cents (e.g., 94.87 = 94 EUR and 87 cents per MWh).",

  "unit": "EUR / MWh",
  "_unit_comment": "Unit of measurement for all price values. EUR = Euro currency, MWh = Megawatt-hour of electricity. This is always 'EUR / MWh' for the price endpoint.",

  "deprecated": false,
  "_deprecated_comment": "Boolean flag indicating API deprecation status. false = API is current and supported. Monitor this flag for API migration planning.",

  "_response_metadata": {
    "request_parameters": {
      "endpoint": "https://api.energy-charts.info/price",
      "bzn": "NL",
      "_bzn_comment": "Bidding Zone code. NL = Netherlands",
      "start": "2025-12-31",
      "_start_comment": "Request start date in ISO 8601 format (YYYY-MM-DD)",
      "end": "2026-01-02",
      "_end_comment": "Request end date in ISO 8601 format (YYYY-MM-DD)"
    },
    "response_characteristics": {
      "http_status": 200,
      "_http_status_comment": "HTTP 200 indicates successful request and valid response",
      "content_type": "application/json",
      "array_length": "Typically 360 elements for 2-day period (288 minimum = 48 hours × 6 intervals/hour)",
      "_array_length_comment": "Each 15-minute interval = 4 prices per hour. 2 days × 24 hours × 4 = 192 minimum",
      "time_interval": "15-minute intervals (900 seconds between timestamps)",
      "_time_interval_comment": "Data granularity is 15 minutes. Consecutive unix_seconds values differ by exactly 900 seconds",
      "timezone": "UTC (Coordinated Universal Time / Zulu time)",
      "_timezone_comment": "All timestamps are in UTC. Convert to local time for display if needed",
      "data_source": "SMARD.de (day-ahead auction)",
      "_data_source_comment": "Data sourced from SMARD.de, which publishes German electricity market data. For Netherlands, this represents APX ENDEX market pricing",
      "market_type": "Day-ahead (DADAM - Day-Ahead Auction)",
      "_market_type_comment": "These are day-ahead prices published ~12:42 CET for the next trading day"
    },
    "critical_validation_rules": {
      "rule_1_array_lengths": "len(unix_seconds) MUST EQUAL len(price)",
      "_rule_1_comment": "Both arrays must be identical length. If mismatch detected, it's a data quality issue",
      "rule_2_timestamp_order": "unix_seconds must be in strictly ascending order",
      "_rule_2_comment": "Each subsequent timestamp must be larger than the previous one",
      "rule_3_timestamp_increment": "Consecutive unix_seconds values must differ by 900 seconds (±some tolerance)",
      "_rule_3_comment": "15-minute intervals should be consistent. Gaps indicate missing data",
      "rule_4_price_alignment": "price[i] corresponds to unix_seconds[i]",
      "_rule_4_comment": "The price at index i is the price for the timestamp at index i. Order matters!",
      "rule_5_price_type": "All price values must be numeric (int or float)",
      "_rule_5_comment": "Null values are rare but valid (indicate missing data). Zero is valid. Negative is rare but valid"
    },
    "example_data_mapping": {
      "data_point_0": {
        "timestamp_unix": 1767135600,
        "timestamp_iso": "2025-12-31T10:00:00Z",
        "price_eur_mwh": 94.87,
        "explanation": "At UTC 10:00 on Dec 31, 2025, the day-ahead price was 94.87 EUR per MWh"
      },
      "data_point_1": {
        "timestamp_unix": 1767136500,
        "timestamp_iso": "2025-12-31T10:15:00Z",
        "price_eur_mwh": 90.31,
        "explanation": "15 minutes later (UTC 10:15), the price declined to 90.31 EUR/MWh"
      },
      "data_point_2": {
        "timestamp_unix": 1767137400,
        "timestamp_iso": "2025-12-31T10:30:00Z",
        "price_eur_mwh": 86.19,
        "explanation": "Another 15 minutes later (UTC 10:30), the price further declined to 86.19 EUR/MWh"
      }
    },
    "parsing_notes": {
      "timestamp_conversion": "Use datetime.fromtimestamp(unix_seconds_value, tz=timezone.utc).isoformat() to convert Unix timestamp to ISO 8601 format (2025-12-31T10:00:00+00:00)",
      "_conversion_comment": "Required for database storage and API responses which typically expect ISO 8601 format",
      "price_storage": "Store as DECIMAL(10,2) or NUMERIC type in database to preserve decimal precision",
      "_price_storage_comment": "Ensure database column can store prices like 94.87 with 2 decimal places",
      "null_handling": "If price is null, treat as missing data. Either skip record or use 0 depending on application logic",
      "_null_handling_comment": "Rare, but can occur for certain time intervals. Validate against len(unix_seconds) == len(price)",
      "array_index_matching": "Always use zip(unix_seconds, price) to maintain index alignment during iteration",
      "_array_index_comment": "Ensures each price is paired with correct timestamp. Do NOT assume index order"
    }
  }
}
